pymycode_packages/__init__.py
pymycode_packages/example.py
pymycode_packages/pdf.py
pymycode_packages-0.0.9.dist-info/METADATA
pymycode_packages-0.0.9.dist-info/WHEEL
pymycode_packages-0.0.9.dist-info/licenses/LICENSE
pymycode_packages-0.0.9.dist-info/RECORD
