Metadata-Version: 2.1
Name: pymycode_packages
Version: 0.0.9
Summary: PyMyCode's scripts
Project-URL: Homepage, https://github.com/PyMyCode
Author-email: Malfire <pymycode@protonmail.com>
License-File: LICENSE
Classifier: License :: OSI Approved :: MIT License
Classifier: Operating System :: OS Independent
Classifier: Programming Language :: Python :: 3
Requires-Python: >=3.7
Requires-Dist: pypdf2~=2.11.2
